ziploc/__init__.py
ziploc/cli.py
ziploc/main.py
ziploc-0.0.2.dist-info/LICENSE
ziploc-0.0.2.dist-info/METADATA
ziploc-0.0.2.dist-info/WHEEL
ziploc-0.0.2.dist-info/entry_points.txt
ziploc-0.0.2.dist-info/top_level.txt
ziploc-0.0.2.dist-info/RECORD
