Metadata-Version: 2.2
Name: ziploc
Version: 0.0.2
Summary: Credential management tool for Python backend
Home-page: https://github.com/cshaxu/ziploc
Author: Xu Ha
Author-email: cshaxu@gmail.com
License: MIT
Classifier: Programming Language :: Python :: 3
Classifier: License :: OSI Approved :: MIT License
Classifier: Operating System :: OS Independent
Requires-Python: >=3.6
License-File: LICENSE
Requires-Dist: pycryptodome>=3.10
Dynamic: author
Dynamic: author-email
Dynamic: classifier
Dynamic: description
Dynamic: description-content-type
Dynamic: home-page
Dynamic: license
Dynamic: requires-dist
Dynamic: requires-python
Dynamic: summary
